src/design/Teclado_BarridoFilas.sv
module SweptRows(
    input logic clk,
    input logic rst,
    output logic [3:0] row
    );

    reg [2:0] state, next_state;
    localparam srow0 = 2'b00, srow1 = 2'b01, srow2 = 2'b10,  srow3 = 2'b11;
 
    initial begin
        state = srow0;
        next_state = srow0;
    end

    always_ff @(posedge clk) begin
        if (rst) begin
            state <= srow0;
        end
        else begin
            state <= next_state;
        end
    end
    
    always @(state) begin
        case (state)
            srow0: begin row = 4'b0001; next_state = srow1; end
            srow1: begin row = 4'b0010; next_state = srow2; end
            srow2: begin row = 4'b0100; next_state = srow3; end
            srow3: begin row = 4'b1000; next_state = srow0; end
            default: next_state = srow0;
        endcase
    end
endmodule

src/design/top.sv
module moduleTop (
    input logic clk,
    input logic rst,
    input logic [3:0] col,
    output logic [3:0] row
);
    
    //wire clk_div;
    //wire row;
    /*wire [3:0] num_o;
    wire [3:0] digit;*/

    /*Debounce Div(
        .num(num),
        .clk(clk),
        .num_o(num_o)
    );*/

    /*FrecDivider Divisor(
        .clk(clk),
        .clk_div(clk_div);
    )*/

    SweptRows Filas(
        .clk(clk),
        .rst(rst),
        .row(row)
    );

    /*KB_Read Teclado(
        .clk(clk),
        .rst(rst),
        .col(col),
        .row(row),
        .num(num)
    );*/
    
endmodule

src/sim/tecladotb.sv
`timescale 1ns/1ps

module kb_tb;
    logic clock;
    logic reset;
    logic [3:0] columna;
    wire [3:0] fila;

    wire num;

    moduleTop kb_top(
        .clk(clock),
        .rst(reset),
        .col(columna),
        .row(fila)
    );

    initial begin
        clock = 1'b0;
        forever #5 clock = ~clock;
    end

    initial begin
        #10
        columna = 4'b0001;
        $display("Tecla: fila=%b", fila);
        
        #2346
        columna = 4'b0010;
        $display("Tecla: fila=%b", fila);
        
        #157
        columna = 4'b0100;
        $display("Tecla: fila=%b", fila);
        
        #270
        columna = 4'b1000;
        $display("Tecla: fila=%b", fila);
        $finish;
    end

    initial begin
        $dumpfile("kb_tb.vcd");
        $dumpvars(0, kb_tb);
    end

endmodule

src/build/kb_tb.vcd
$date
	Tue Oct 01 18:42:49 2024
$end
$version
	Icarus Verilog
$end
$timescale
	1ps
$end
$scope module kb_tb $end
$var wire 4 ! fila [3:0] $end
$var reg 1 " clock $end
$var reg 4 # columna [3:0] $end
$var reg 1 $ reset $end
$scope module kb_top $end
$var wire 1 " clk $end
$var wire 4 % col [3:0] $end
$var wire 1 $ rst $end
$var wire 4 & row [3:0] $end
$scope module Filas $end
$var wire 1 " clk $end
$var wire 1 $ rst $end
$var parameter 2 ' srow0 $end
$var parameter 2 ( srow1 $end
$var parameter 2 ) srow2 $end
$var parameter 2 * srow3 $end
$var reg 3 + next_state [2:0] $end
$var reg 4 , row [3:0] $end
$var reg 3 - state [2:0] $end
$upscope $end
$upscope $end
$upscope $end
$enddefinitions $end
$comment Show the parameter values. $end
$dumpall
b11 *
b10 )
b1 (
b0 '
$end
#0
$dumpvars
b0 -
b1 ,
b1 +
b1 &
bx %
x$
bx #
0"
b1 !
$end
#5000
b10 +
b10 !
b10 &
b10 ,
b1 -
1"
#10000
0"
b1 #
b1 %
#15000
b11 +
b100 !
b100 &
b100 ,
b10 -
1"
#20000
0"
#25000
b0 +
b1000 !
b1000 &
b1000 ,
b11 -
1"
#30000
0"
#35000
b1 +
b1 !
b1 &
b1 ,
b0 -
1"
#40000
0"
#45000
b10 +
b10 !
b10 &
b10 ,
b1 -
1"
#50000
0"
#55000
b11 +
b100 !
b100 &
b100 ,
b10 -
1"
#60000
0"
#65000
b0 +
b1000 !
b1000 &
b1000 ,
b11 -
1"
#70000
0"
#75000
b1 +
b1 !
b1 &
b1 ,
b0 -
1"
#80000
0"
#85000
b10 +
b10 !
b10 &
b10 ,
b1 -
1"
#90000
0"
#95000
b11 +
b100 !
b100 &
b100 ,
b10 -
1"
#100000
0"
#105000
b0 +
b1000 !
b1000 &
b1000 ,
b11 -
1"
#110000
0"
#115000
b1 +
b1 !
b1 &
b1 ,
b0 -
1"
#120000
0"
#125000
b10 +
b10 !
b10 &
b10 ,
b1 -
1"
#130000
0"
#135000
b11 +
b100 !
b100 &
b100 ,
b10 -
1"
#140000
0"
#145000
b0 +
b1000 !
b1000 &
b1000 ,
b11 -
1"
#150000
0"
#155000
b1 +
b1 !
b1 &
b1 ,
b0 -
1"
#160000
0"
#165000
b10 +
b10 !
b10 &
b10 ,
b1 -
1"
#170000
0"
#175000
b11 +
b100 !
b100 &
b100 ,
b10 -
1"
#180000
0"
#185000
b0 +
b1000 !
b1000 &
b1000 ,
b11 -
1"
#190000
0"
#195000
b1 +
b1 !
b1 &
b1 ,
b0 -
1"
#200000
0"
#205000
b10 +
b10 !
b10 &
b10 ,
b1 -
1"
#210000
0"
#215000
b11 +
b100 !
b100 &
b100 ,
b10 -
1"
#220000
0"
#225000
b0 +
b1000 !
b1000 &
b1000 ,
b11 -
1"
#230000
0"
#235000
b1 +
b1 !
b1 &
b1 ,
b0 -
1"
#240000
0"
#245000
b10 +
b10 !
b10 &
b10 ,
b1 -
1"
#250000
0"
#255000
b11 +
b100 !
b100 &
b100 ,
b10 -
1"
#260000
0"
#265000
b0 +
b1000 !
b1000 &
b1000 ,
b11 -
1"
#270000
0"
#275000
b1 +
b1 !
b1 &
b1 ,
b0 -
1"
#280000
0"
#285000
b10 +
b10 !
b10 &
b10 ,
b1 -
1"
#290000
0"
#295000
b11 +
b100 !
b100 &
b100 ,
b10 -
1"
#300000
0"
#305000
b0 +
b1000 !
b1000 &
b1000 ,
b11 -
1"
#310000
0"
#315000
b1 +
b1 !
b1 &
b1 ,
b0 -
1"
#320000
0"
#325000
b10 +
b10 !
b10 &
b10 ,
b1 -
1"
#330000
0"
#335000
b11 +
b100 !
b100 &
b100 ,
b10 -
1"
#340000
0"
#345000
b0 +
b1000 !
b1000 &
b1000 ,
b11 -
1"
#350000
0"
#355000
b1 +
b1 !
b1 &
b1 ,
b0 -
1"
#360000
0"
#365000
b10 +
b10 !
b10 &
b10 ,
b1 -
1"
#370000
0"
#375000
b11 +
b100 !
b100 &
b100 ,
b10 -
1"
#380000
0"
#385000
b0 +
b1000 !
b1000 &
b1000 ,
b11 -
1"
#390000
0"
#395000
b1 +
b1 !
b1 &
b1 ,
b0 -
1"
#400000
0"
#405000
b10 +
b10 !
b10 &
b10 ,
b1 -
1"
#410000
0"
#415000
b11 +
b100 !
b100 &
b100 ,
b10 -
1"
#420000
0"
#425000
b0 +
b1000 !
b1000 &
b1000 ,
b11 -
1"
#430000
0"
#435000
b1 +
b1 !
b1 &
b1 ,
b0 -
1"
#440000
0"
#445000
b10 +
b10 !
b10 &
b10 ,
b1 -
1"
#450000
0"
#455000
b11 +
b100 !
b100 &
b100 ,
b10 -
1"
#460000
0"
#465000
b0 +
b1000 !
b1000 &
b1000 ,
b11 -
1"
#470000
0"
#475000
b1 +
b1 !
b1 &
b1 ,
b0 -
1"
#480000
0"
#485000
b10 +
b10 !
b10 &
b10 ,
b1 -
1"
#490000
0"
#495000
b11 +
b100 !
b100 &
b100 ,
b10 -
1"
#500000
0"
#505000
b0 +
b1000 !
b1000 &
b1000 ,
b11 -
1"
#510000
0"
#515000
b1 +
b1 !
b1 &
b1 ,
b0 -
1"
#520000
0"
#525000
b10 +
b10 !
b10 &
b10 ,
b1 -
1"
#530000
0"
#535000
b11 +
b100 !
b100 &
b100 ,
b10 -
1"
#540000
0"
#545000
b0 +
b1000 !
b1000 &
b1000 ,
b11 -
1"
#550000
0"
#555000
b1 +
b1 !
b1 &
b1 ,
b0 -
1"
#560000
0"
#565000
b10 +
b10 !
b10 &
b10 ,
b1 -
1"
#570000
0"
#575000
b11 +
b100 !
b100 &
b100 ,
b10 -
1"
#580000
0"
#585000
b0 +
b1000 !
b1000 &
b1000 ,
b11 -
1"
#590000
0"
#595000
b1 +
b1 !
b1 &
b1 ,
b0 -
1"
#600000
0"
#605000
b10 +
b10 !
b10 &
b10 ,
b1 -
1"
#610000
0"
#615000
b11 +
b100 !
b100 &
b100 ,
b10 -
1"
#620000
0"
#625000
b0 +
b1000 !
b1000 &
b1000 ,
b11 -
1"
#630000
0"
#635000
b1 +
b1 !
b1 &
b1 ,
b0 -
1"
#640000
0"
#645000
b10 +
b10 !
b10 &
b10 ,
b1 -
1"
#650000
0"
#655000
b11 +
b100 !
b100 &
b100 ,
b10 -
1"
#660000
0"
#665000
b0 +
b1000 !
b1000 &
b1000 ,
b11 -
1"
#670000
0"
#675000
b1 +
b1 !
b1 &
b1 ,
b0 -
1"
#680000
0"
#685000
b10 +
b10 !
b10 &
b10 ,
b1 -
1"
#690000
0"
#695000
b11 +
b100 !
b100 &
b100 ,
b10 -
1"
#700000
0"
#705000
b0 +
b1000 !
b1000 &
b1000 ,
b11 -
1"
#710000
0"
#715000
b1 +
b1 !
b1 &
b1 ,
b0 -
1"
#720000
0"
#725000
b10 +
b10 !
b10 &
b10 ,
b1 -
1"
#730000
0"
#735000
b11 +
b100 !
b100 &
b100 ,
b10 -
1"
#740000
0"
#745000
b0 +
b1000 !
b1000 &
b1000 ,
b11 -
1"
#750000
0"
#755000
b1 +
b1 !
b1 &
b1 ,
b0 -
1"
#760000
0"
#765000
b10 +
b10 !
b10 &
b10 ,
b1 -
1"
#770000
0"
#775000
b11 +
b100 !
b100 &
b100 ,
b10 -
1"
#780000
0"
#785000
b0 +
b1000 !
b1000 &
b1000 ,
b11 -
1"
#790000
0"
#795000
b1 +
b1 !
b1 &
b1 ,
b0 -
1"
#800000
0"
#805000
b10 +
b10 !
b10 &
b10 ,
b1 -
1"
#810000
0"
#815000
b11 +
b100 !
b100 &
b100 ,
b10 -
1"
#820000
0"
#825000
b0 +
b1000 !
b1000 &
b1000 ,
b11 -
1"
#830000
0"
#835000
b1 +
b1 !
b1 &
b1 ,
b0 -
1"
#840000
0"
#845000
b10 +
b10 !
b10 &
b10 ,
b1 -
1"
#850000
0"
#855000
b11 +
b100 !
b100 &
b100 ,
b10 -
1"
#860000
0"
#865000
b0 +
b1000 !
b1000 &
b1000 ,
b11 -
1"
#870000
0"
#875000
b1 +
b1 !
b1 &
b1 ,
b0 -
1"
#880000
0"
#885000
b10 +
b10 !
b10 &
b10 ,
b1 -
1"
#890000
0"
#895000
b11 +
b100 !
b100 &
b100 ,
b10 -
1"
#900000
0"
#905000
b0 +
b1000 !
b1000 &
b1000 ,
b11 -
1"
#910000
0"
#915000
b1 +
b1 !
b1 &
b1 ,
b0 -
1"
#920000
0"
#925000
b10 +
b10 !
b10 &
b10 ,
b1 -
1"
#930000
0"
#935000
b11 +
b100 !
b100 &
b100 ,
b10 -
1"
#940000
0"
#945000
b0 +
b1000 !
b1000 &
b1000 ,
b11 -
1"
#950000
0"
#955000
b1 +
b1 !
b1 &
b1 ,
b0 -
1"
#960000
0"
#965000
b10 +
b10 !
b10 &
b10 ,
b1 -
1"
#970000
0"
#975000
b11 +
b100 !
b100 &
b100 ,
b10 -
1"
#980000
0"
#985000
b0 +
b1000 !
b1000 &
b1000 ,
b11 -
1"
#990000
0"
#995000
b1 +
b1 !
b1 &
b1 ,
b0 -
1"
#1000000
0"
#1005000
b10 +
b10 !
b10 &
b10 ,
b1 -
1"
#1010000
0"
#1015000
b11 +
b100 !
b100 &
b100 ,
b10 -
1"
#1020000
0"
#1025000
b0 +
b1000 !
b1000 &
b1000 ,
b11 -
1"
#1030000
0"
#1035000
b1 +
b1 !
b1 &
b1 ,
b0 -
1"
#1040000
0"
#1045000
b10 +
b10 !
b10 &
b10 ,
b1 -
1"
#1050000
0"
#1055000
b11 +
b100 !
b100 &
b100 ,
b10 -
1"
#1060000
0"
#1065000
b0 +
b1000 !
b1000 &
b1000 ,
b11 -
1"
#1070000
0"
#1075000
b1 +
b1 !
b1 &
b1 ,
b0 -
1"
#1080000
0"
#1085000
b10 +
b10 !
b10 &
b10 ,
b1 -
1"
#1090000
0"
#1095000
b11 +
b100 !
b100 &
b100 ,
b10 -
1"
#1100000
0"
#1105000
b0 +
b1000 !
b1000 &
b1000 ,
b11 -
1"
#1110000
0"
#1115000
b1 +
b1 !
b1 &
b1 ,
b0 -
1"
#1120000
0"
#1125000
b10 +
b10 !
b10 &
b10 ,
b1 -
1"
#1130000
0"
#1135000
b11 +
b100 !
b100 &
b100 ,
b10 -
1"
#1140000
0"
#1145000
b0 +
b1000 !
b1000 &
b1000 ,
b11 -
1"
#1150000
0"
#1155000
b1 +
b1 !
b1 &
b1 ,
b0 -
1"
#1160000
0"
#1165000
b10 +
b10 !
b10 &
b10 ,
b1 -
1"
#1170000
0"
#1175000
b11 +
b100 !
b100 &
b100 ,
b10 -
1"
#1180000
0"
#1185000
b0 +
b1000 !
b1000 &
b1000 ,
b11 -
1"
#1190000
0"
#1195000
b1 +
b1 !
b1 &
b1 ,
b0 -
1"
#1200000
0"
#1205000
b10 +
b10 !
b10 &
b10 ,
b1 -
1"
#1210000
0"
#1215000
b11 +
b100 !
b100 &
b100 ,
b10 -
1"
#1220000
0"
#1225000
b0 +
b1000 !
b1000 &
b1000 ,
b11 -
1"
#1230000
0"
#1235000
b1 +
b1 !
b1 &
b1 ,
b0 -
1"
#1240000
0"
#1245000
b10 +
b10 !
b10 &
b10 ,
b1 -
1"
#1250000
0"
#1255000
b11 +
b100 !
b100 &
b100 ,
b10 -
1"
#1260000
0"
#1265000
b0 +
b1000 !
b1000 &
b1000 ,
b11 -
1"
#1270000
0"
#1275000
b1 +
b1 !
b1 &
b1 ,
b0 -
1"
#1280000
0"
#1285000
b10 +
b10 !
b10 &
b10 ,
b1 -
1"
#1290000
0"
#1295000
b11 +
b100 !
b100 &
b100 ,
b10 -
1"
#1300000
0"
#1305000
b0 +
b1000 !
b1000 &
b1000 ,
b11 -
1"
#1310000
0"
#1315000
b1 +
b1 !
b1 &
b1 ,
b0 -
1"
#1320000
0"
#1325000
b10 +
b10 !
b10 &
b10 ,
b1 -
1"
#1330000
0"
#1335000
b11 +
b100 !
b100 &
b100 ,
b10 -
1"
#1340000
0"
#1345000
b0 +
b1000 !
b1000 &
b1000 ,
b11 -
1"
#1350000
0"
#1355000
b1 +
b1 !
b1 &
b1 ,
b0 -
1"
#1360000
0"
#1365000
b10 +
b10 !
b10 &
b10 ,
b1 -
1"
#1370000
0"
#1375000
b11 +
b100 !
b100 &
b100 ,
b10 -
1"
#1380000
0"
#1385000
b0 +
b1000 !
b1000 &
b1000 ,
b11 -
1"
#1390000
0"
#1395000
b1 +
b1 !
b1 &
b1 ,
b0 -
1"
#1400000
0"
#1405000
b10 +
b10 !
b10 &
b10 ,
b1 -
1"
#1410000
0"
#1415000
b11 +
b100 !
b100 &
b100 ,
b10 -
1"
#1420000
0"
#1425000
b0 +
b1000 !
b1000 &
b1000 ,
b11 -
1"
#1430000
0"
#1435000
b1 +
b1 !
b1 &
b1 ,
b0 -
1"
#1440000
0"
#1445000
b10 +
b10 !
b10 &
b10 ,
b1 -
1"
#1450000
0"
#1455000
b11 +
b100 !
b100 &
b100 ,
b10 -
1"
#1460000
0"
#1465000
b0 +
b1000 !
b1000 &
b1000 ,
b11 -
1"
#1470000
0"
#1475000
b1 +
b1 !
b1 &
b1 ,
b0 -
1"
#1480000
0"
#1485000
b10 +
b10 !
b10 &
b10 ,
b1 -
1"
#1490000
0"
#1495000
b11 +
b100 !
b100 &
b100 ,
b10 -
1"
#1500000
0"
#1505000
b0 +
b1000 !
b1000 &
b1000 ,
b11 -
1"
#1510000
0"
#1515000
b1 +
b1 !
b1 &
b1 ,
b0 -
1"
#1520000
0"
#1525000
b10 +
b10 !
b10 &
b10 ,
b1 -
1"
#1530000
0"
#1535000
b11 +
b100 !
b100 &
b100 ,
b10 -
1"
#1540000
0"
#1545000
b0 +
b1000 !
b1000 &
b1000 ,
b11 -
1"
#1550000
0"
#1555000
b1 +
b1 !
b1 &
b1 ,
b0 -
1"
#1560000
0"
#1565000
b10 +
b10 !
b10 &
b10 ,
b1 -
1"
#1570000
0"
#1575000
b11 +
b100 !
b100 &
b100 ,
b10 -
1"
#1580000
0"
#1585000
b0 +
b1000 !
b1000 &
b1000 ,
b11 -
1"
#1590000
0"
#1595000
b1 +
b1 !
b1 &
b1 ,
b0 -
1"
#1600000
0"
#1605000
b10 +
b10 !
b10 &
b10 ,
b1 -
1"
#1610000
0"
#1615000
b11 +
b100 !
b100 &
b100 ,
b10 -
1"
#1620000
0"
#1625000
b0 +
b1000 !
b1000 &
b1000 ,
b11 -
1"
#1630000
0"
#1635000
b1 +
b1 !
b1 &
b1 ,
b0 -
1"
#1640000
0"
#1645000
b10 +
b10 !
b10 &
b10 ,
b1 -
1"
#1650000
0"
#1655000
b11 +
b100 !
b100 &
b100 ,
b10 -
1"
#1660000
0"
#1665000
b0 +
b1000 !
b1000 &
b1000 ,
b11 -
1"
#1670000
0"
#1675000
b1 +
b1 !
b1 &
b1 ,
b0 -
1"
#1680000
0"
#1685000
b10 +
b10 !
b10 &
b10 ,
b1 -
1"
#1690000
0"
#1695000
b11 +
b100 !
b100 &
b100 ,
b10 -
1"
#1700000
0"
#1705000
b0 +
b1000 !
b1000 &
b1000 ,
b11 -
1"
#1710000
0"
#1715000
b1 +
b1 !
b1 &
b1 ,
b0 -
1"
#1720000
0"
#1725000
b10 +
b10 !
b10 &
b10 ,
b1 -
1"
#1730000
0"
#1735000
b11 +
b100 !
b100 &
b100 ,
b10 -
1"
#1740000
0"
#1745000
b0 +
b1000 !
b1000 &
b1000 ,
b11 -
1"
#1750000
0"
#1755000
b1 +
b1 !
b1 &
b1 ,
b0 -
1"
#1760000
0"
#1765000
b10 +
b10 !
b10 &
b10 ,
b1 -
1"
#1770000
0"
#1775000
b11 +
b100 !
b100 &
b100 ,
b10 -
1"
#1780000
0"
#1785000
b0 +
b1000 !
b1000 &
b1000 ,
b11 -
1"
#1790000
0"
#1795000
b1 +
b1 !
b1 &
b1 ,
b0 -
1"
#1800000
0"
#1805000
b10 +
b10 !
b10 &
b10 ,
b1 -
1"
#1810000
0"
#1815000
b11 +
b100 !
b100 &
b100 ,
b10 -
1"
#1820000
0"
#1825000
b0 +
b1000 !
b1000 &
b1000 ,
b11 -
1"
#1830000
0"
#1835000
b1 +
b1 !
b1 &
b1 ,
b0 -
1"
#1840000
0"
#1845000
b10 +
b10 !
b10 &
b10 ,
b1 -
1"
#1850000
0"
#1855000
b11 +
b100 !
b100 &
b100 ,
b10 -
1"
#1860000
0"
#1865000
b0 +
b1000 !
b1000 &
b1000 ,
b11 -
1"
#1870000
0"
#1875000
b1 +
b1 !
b1 &
b1 ,
b0 -
1"
#1880000
0"
#1885000
b10 +
b10 !
b10 &
b10 ,
b1 -
1"
#1890000
0"
#1895000
b11 +
b100 !
b100 &
b100 ,
b10 -
1"
#1900000
0"
#1905000
b0 +
b1000 !
b1000 &
b1000 ,
b11 -
1"
#1910000
0"
#1915000
b1 +
b1 !
b1 &
b1 ,
b0 -
1"
#1920000
0"
#1925000
b10 +
b10 !
b10 &
b10 ,
b1 -
1"
#1930000
0"
#1935000
b11 +
b100 !
b100 &
b100 ,
b10 -
1"
#1940000
0"
#1945000
b0 +
b1000 !
b1000 &
b1000 ,
b11 -
1"
#1950000
0"
#1955000
b1 +
b1 !
b1 &
b1 ,
b0 -
1"
#1960000
0"
#1965000
b10 +
b10 !
b10 &
b10 ,
b1 -
1"
#1970000
0"
#1975000
b11 +
b100 !
b100 &
b100 ,
b10 -
1"
#1980000
0"
#1985000
b0 +
b1000 !
b1000 &
b1000 ,
b11 -
1"
#1990000
0"
#1995000
b1 +
b1 !
b1 &
b1 ,
b0 -
1"
#2000000
0"
#2005000
b10 +
b10 !
b10 &
b10 ,
b1 -
1"
#2010000
0"
#2015000
b11 +
b100 !
b100 &
b100 ,
b10 -
1"
#2020000
0"
#2025000
b0 +
b1000 !
b1000 &
b1000 ,
b11 -
1"
#2030000
0"
#2035000
b1 +
b1 !
b1 &
b1 ,
b0 -
1"
#2040000
0"
#2045000
b10 +
b10 !
b10 &
b10 ,
b1 -
1"
#2050000
0"
#2055000
b11 +
b100 !
b100 &
b100 ,
b10 -
1"
#2060000
0"
#2065000
b0 +
b1000 !
b1000 &
b1000 ,
b11 -
1"
#2070000
0"
#2075000
b1 +
b1 !
b1 &
b1 ,
b0 -
1"
#2080000
0"
#2085000
b10 +
b10 !
b10 &
b10 ,
b1 -
1"
#2090000
0"
#2095000
b11 +
b100 !
b100 &
b100 ,
b10 -
1"
#2100000
0"
#2105000
b0 +
b1000 !
b1000 &
b1000 ,
b11 -
1"
#2110000
0"
#2115000
b1 +
b1 !
b1 &
b1 ,
b0 -
1"
#2120000
0"
#2125000
b10 +
b10 !
b10 &
b10 ,
b1 -
1"
#2130000
0"
#2135000
b11 +
b100 !
b100 &
b100 ,
b10 -
1"
#2140000
0"
#2145000
b0 +
b1000 !
b1000 &
b1000 ,
b11 -
1"
#2150000
0"
#2155000
b1 +
b1 !
b1 &
b1 ,
b0 -
1"
#2160000
0"
#2165000
b10 +
b10 !
b10 &
b10 ,
b1 -
1"
#2170000
0"
#2175000
b11 +
b100 !
b100 &
b100 ,
b10 -
1"
#2180000
0"
#2185000
b0 +
b1000 !
b1000 &
b1000 ,
b11 -
1"
#2190000
0"
#2195000
b1 +
b1 !
b1 &
b1 ,
b0 -
1"
#2200000
0"
#2205000
b10 +
b10 !
b10 &
b10 ,
b1 -
1"
#2210000
0"
#2215000
b11 +
b100 !
b100 &
b100 ,
b10 -
1"
#2220000
0"
#2225000
b0 +
b1000 !
b1000 &
b1000 ,
b11 -
1"
#2230000
0"
#2235000
b1 +
b1 !
b1 &
b1 ,
b0 -
1"
#2240000
0"
#2245000
b10 +
b10 !
b10 &
b10 ,
b1 -
1"
#2250000
0"
#2255000
b11 +
b100 !
b100 &
b100 ,
b10 -
1"
#2260000
0"
#2265000
b0 +
b1000 !
b1000 &
b1000 ,
b11 -
1"
#2270000
0"
#2275000
b1 +
b1 !
b1 &
b1 ,
b0 -
1"
#2280000
0"
#2285000
b10 +
b10 !
b10 &
b10 ,
b1 -
1"
#2290000
0"
#2295000
b11 +
b100 !
b100 &
b100 ,
b10 -
1"
#2300000
0"
#2305000
b0 +
b1000 !
b1000 &
b1000 ,
b11 -
1"
#2310000
0"
#2315000
b1 +
b1 !
b1 &
b1 ,
b0 -
1"
#2320000
0"
#2325000
b10 +
b10 !
b10 &
b10 ,
b1 -
1"
#2330000
0"
#2335000
b11 +
b100 !
b100 &
b100 ,
b10 -
1"
#2340000
0"
#2345000
b0 +
b1000 !
b1000 &
b1000 ,
b11 -
1"
#2350000
0"
#2355000
b1 +
b1 !
b1 &
b1 ,
b0 -
1"
#2356000
b10 #
b10 %
#2360000
0"
#2365000
b10 +
b10 !
b10 &
b10 ,
b1 -
1"
#2370000
0"
#2375000
b11 +
b100 !
b100 &
b100 ,
b10 -
1"
#2380000
0"
#2385000
b0 +
b1000 !
b1000 &
b1000 ,
b11 -
1"
#2390000
0"
#2395000
b1 +
b1 !
b1 &
b1 ,
b0 -
1"
#2400000
0"
#2405000
b10 +
b10 !
b10 &
b10 ,
b1 -
1"
#2410000
0"
#2415000
b11 +
b100 !
b100 &
b100 ,
b10 -
1"
#2420000
0"
#2425000
b0 +
b1000 !
b1000 &
b1000 ,
b11 -
1"
#2430000
0"
#2435000
b1 +
b1 !
b1 &
b1 ,
b0 -
1"
#2440000
0"
#2445000
b10 +
b10 !
b10 &
b10 ,
b1 -
1"
#2450000
0"
#2455000
b11 +
b100 !
b100 &
b100 ,
b10 -
1"
#2460000
0"
#2465000
b0 +
b1000 !
b1000 &
b1000 ,
b11 -
1"
#2470000
0"
#2475000
b1 +
b1 !
b1 &
b1 ,
b0 -
1"
#2480000
0"
#2485000
b10 +
b10 !
b10 &
b10 ,
b1 -
1"
#2490000
0"
#2495000
b11 +
b100 !
b100 &
b100 ,
b10 -
1"
#2500000
0"
#2505000
b0 +
b1000 !
b1000 &
b1000 ,
b11 -
1"
#2510000
0"
#2513000
b100 #
b100 %
#2515000
b1 +
b1 !
b1 &
b1 ,
b0 -
1"
#2520000
0"
#2525000
b10 +
b10 !
b10 &
b10 ,
b1 -
1"
#2530000
0"
#2535000
b11 +
b100 !
b100 &
b100 ,
b10 -
1"
#2540000
0"
#2545000
b0 +
b1000 !
b1000 &
b1000 ,
b11 -
1"
#2550000
0"
#2555000
b1 +
b1 !
b1 &
b1 ,
b0 -
1"
#2560000
0"
#2565000
b10 +
b10 !
b10 &
b10 ,
b1 -
1"
#2570000
0"
#2575000
b11 +
b100 !
b100 &
b100 ,
b10 -
1"
#2580000
0"
#2585000
b0 +
b1000 !
b1000 &
b1000 ,
b11 -
1"
#2590000
0"
#2595000
b1 +
b1 !
b1 &
b1 ,
b0 -
1"
#2600000
0"
#2605000
b10 +
b10 !
b10 &
b10 ,
b1 -
1"
#2610000
0"
#2615000
b11 +
b100 !
b100 &
b100 ,
b10 -
1"
#2620000
0"
#2625000
b0 +
b1000 !
b1000 &
b1000 ,
b11 -
1"
#2630000
0"
#2635000
b1 +
b1 !
b1 &
b1 ,
b0 -
1"
#2640000
0"
#2645000
b10 +
b10 !
b10 &
b10 ,
b1 -
1"
#2650000
0"
#2655000
b11 +
b100 !
b100 &
b100 ,
b10 -
1"
#2660000
0"
#2665000
b0 +
b1000 !
b1000 &
b1000 ,
b11 -
1"
#2670000
0"
#2675000
b1 +
b1 !
b1 &
b1 ,
b0 -
1"
#2680000
0"
#2685000
b10 +
b10 !
b10 &
b10 ,
b1 -
1"
#2690000
0"
#2695000
b11 +
b100 !
b100 &
b100 ,
b10 -
1"
#2700000
0"
#2705000
b0 +
b1000 !
b1000 &
b1000 ,
b11 -
1"
#2710000
0"
#2715000
b1 +
b1 !
b1 &
b1 ,
b0 -
1"
#2720000
0"
#2725000
b10 +
b10 !
b10 &
b10 ,
b1 -
1"
#2730000
0"
#2735000
b11 +
b100 !
b100 &
b100 ,
b10 -
1"
#2740000
0"
#2745000
b0 +
b1000 !
b1000 &
b1000 ,
b11 -
1"
#2750000
0"
#2755000
b1 +
b1 !
b1 &
b1 ,
b0 -
1"
#2760000
0"
#2765000
b10 +
b10 !
b10 &
b10 ,
b1 -
1"
#2770000
0"
#2775000
b11 +
b100 !
b100 &
b100 ,
b10 -
1"
#2780000
0"
#2783000
b1000 #
b1000 %
