src/design/Sumador_Suma.sv
module suma (
    input logic clk,    // senal de reloj
    input logic [15:0] num1,
    input logic [15:0] num2,
    output logic [15:0] resultado
);

    reg [15:0] num;

    // asegura que suma solo se realice al inicio de cada ciclo de reloj
    always_ff @( posedge clk ) begin
        if (num1 != 0 && num2 != 0) begin
           num <= num1+num2; 
        end
    end

    assign resultado = num;

endmodule

src/design/Sumador_Display7seg.sv
module display (
    input logic clk,
    input logic [15:0] bcd,
    output logic [3:0] anodos,
    output logic [6:0] segmentos
);
    logic [3:0] a;
    logic [3:0] b;
    logic [3:0] c;
    reg [3:0] digit;
    reg [1:0] select=0;

    assign a = bcd[11:8];
    assign b = bcd[7:4];
    assign c = bcd[3:0];

    always_ff @(posedge clk) begin
        select <= select + 1'b1; 
    end

    //controla activar un display a la vez
    always_comb begin
        case (select) // traduce c/d numero BCD al 7seg correspondiente
            2'b00: begin
                anodos = 4'b0001; // Activar display 1
                digit = 4'b0000;
            end
            2'b01: begin
                anodos = 4'b0010; // Activar display 2
                digit = a;
            end
            2'b10: begin
                anodos = 4'b0100; // Activar display 3
                digit = b;
            end
            2'b11: begin 
                anodos = 4'b1000; // Activar display 4
                digit = c;
            end
            default: begin
                anodos = 4'b0001;
                digit = 4'b1111;
            end
        endcase  
    end

    // controla el segmentos de acuerdo con el digito BCD
    always_comb begin
        case(digit)
            4'd0: segmentos = 7'b0111111; // 0
            4'd1: segmentos = 7'b0000110; // 1
            4'd2: segmentos = 7'b1011011; // 2
            4'd3: segmentos = 7'b1001111; // 3
            4'd4: segmentos = 7'b1100110; // 4
            4'd5: segmentos = 7'b1101101; // 5
            4'd6: segmentos = 7'b1111101; // 6
            4'd7: segmentos = 7'b0000111; // 7
            4'd8: segmentos = 7'b1111111; // 8
            4'd9: segmentos = 7'b1101111; // 9
            default: segmentos = 7'b1111111; // Desactiva los segmentos
        endcase
    end

endmodule

src/design/D_LectorNum.sv
module LectorDigitos (
    input logic clk,
    input logic operador,
    input logic [3:0] col,
    output logic [15:0] num
);

    reg [1:0] cont = 0;

    always_ff @(posedge clk) begin
        if (operador) begin
           cont <= cont + 1'b1; 
        end
    end

    always_comb begin
        case (cont)
            2'b00: begin num = 0; end
            2'b01: begin
                num = {num[12:0],col};
            end
            2'b10: begin
                num = {num[12:0],col};
            end
            2'b11: begin num = {num[12:0],col}; end
            default: num = 0;
        endcase
    end

endmodule

src/design/top_prueba.sv
module SumaTop (
    input logic clk,
    input logic rst,
    input logic operador,
    input logic [3:0] col,
    output logic [3:0] anodos,
    output logic [6:0] segmentos
);
    
    reg [1:0] contador;
    reg [15:0] numero;
    logic [15:0] num1;
    logic [15:0] num2;
    logic [15:0] resultado;

    LectorDigitos Entradas(
        .clk(clk),
        .operador(operador),
        .col(col),
        .num(num1)
        );
    
    display Sevens(
        .clk(clk),
        .bcd(num1),
        .anodos(anodos),
        .segmentos(segmentos)
        );
        
    suma Adder(
        .clk(clk),
        .num1(num1),
        .num2(num2),
        .resultado(numero)
        );

    always_ff @(posedge clk) begin
        if (contador == 0) begin
            resultado <= num1;
        end
        else if (contador == 2'b01) begin
            resultado <= num2;
        end
        else if (contador == 2'b10) begin
            num2 <= resultado;
        end
        else if (contador == 2'b11) begin
            resultado <= numero;
        end        
    end

    always @(~rst) begin
        contador <= contador + 1'b1;
    end

endmodule

src/sim/pruebatb.sv
`timescale 1ns/1ps

module pruebatb;
    // Declaración de señales
    logic clock;
    logic reset;
    logic btn_digits;
    logic [3:0] num_ent;
    logic [15:0] num1, num2;
    logic [15:0] resultado;
    logic [3:0] anode;
    logic [6:0] seg;

    // Instancia del módulo sumador que queremos probar
    SumaTop tsumador (
        .clk(clock),
        .rst(reset),
        .operador(btn_digits),
        .col(num_ent),
        .anodos(anode),
        .segmentos(seg)
    );

    // Generación del reloj (un ciclo cada 10 unidades de tiempo)
    always #5 clock = ~clock;

    // Bloque inicial que define el comportamiento del test
    initial begin
        // Inicializar señales
        clock = 0;
        num_ent = 4'b0110;
        btn_digits = ~btn_digits;
        num_ent = 4'b0001;
        btn_digits = ~btn_digits;
        num_ent = 4'b0000;
        btn_digits = ~btn_digits;
        num_ent = 4'b0000;
         
        $display("Prueba 1: num1 = %d, num2 = %d, resultado = %d | %b", num1, num2, resultado, resultado);
        #40;

        num_ent = 4'b0010;
        btn_digits = ~btn_digits;
        num_ent = 4'b0011;
        btn_digits = ~btn_digits;
        num_ent = 4'b0000;
        btn_digits = ~btn_digits;
        num_ent = 4'b0000;
         
        $display("Prueba : num1 = %d, num2 = %d, resultado = %d | %b", num1, num2, resultado, resultado);
        #40;

        $finish;
    end

    // Monitoreo de señales
    initial begin
        $monitor("Tiempo: %0t | Anodos = %b | Segmentos = %b", $time, anode, seg);
    end

    initial begin
        $dumpfile("pruebatb.vcd");
        $dumpvars(0, pruebatb);
    end
endmodule

src/build/pruebatb.vcd
$date
	Thu Oct 03 09:15:08 2024
$end
$version
	Icarus Verilog
$end
$timescale
	1ps
$end
$scope module pruebatb $end
$var wire 7 ! seg [6:0] $end
$var wire 4 " anode [3:0] $end
$var reg 1 # btn_digits $end
$var reg 1 $ clock $end
$var reg 16 % num1 [15:0] $end
$var reg 16 & num2 [15:0] $end
$var reg 4 ' num_ent [3:0] $end
$var reg 1 ( reset $end
$var reg 16 ) resultado [15:0] $end
$scope module tsumador $end
$var wire 1 $ clk $end
$var wire 4 * col [3:0] $end
$var wire 1 # operador $end
$var wire 1 ( rst $end
$var wire 7 + segmentos [6:0] $end
$var wire 16 , numero [15:0] $end
$var wire 16 - num1 [15:0] $end
$var wire 4 . anodos [3:0] $end
$var reg 2 / contador [1:0] $end
$var reg 16 0 num2 [15:0] $end
$var reg 16 1 resultado [15:0] $end
$scope module Adder $end
$var wire 1 $ clk $end
$var wire 16 2 num2 [15:0] $end
$var wire 16 3 resultado [15:0] $end
$var wire 16 4 num1 [15:0] $end
$var reg 16 5 num [15:0] $end
$upscope $end
$scope module Entradas $end
$var wire 1 $ clk $end
$var wire 4 6 col [3:0] $end
$var wire 1 # operador $end
$var reg 2 7 cont [1:0] $end
$var reg 16 8 num [15:0] $end
$upscope $end
$scope module Sevens $end
$var wire 16 9 bcd [15:0] $end
$var wire 1 $ clk $end
$var wire 4 : c [3:0] $end
$var wire 4 ; b [3:0] $end
$var wire 4 < a [3:0] $end
$var reg 4 = anodos [3:0] $end
$var reg 4 > digit [3:0] $end
$var reg 7 ? segmentos [6:0] $end
$var reg 2 @ select [1:0] $end
$upscope $end
$upscope $end
$upscope $end
$enddefinitions $end
$comment Show the parameter values. $end
$dumpall
$end
#0
$dumpvars
b0 @
b111111 ?
b0 >
b1 =
b0 <
b0 ;
b0 :
b0 9
b0 8
b0 7
b0 6
bx 5
b0 4
bx 3
bx 2
bx 1
bx 0
bx /
b1 .
b0 -
bx ,
b111111 +
b0 *
bx )
x(
b0 '
bx &
bx %
0$
x#
b1 "
b111111 !
$end
#5000
b10 "
b10 .
b10 =
b1 @
1$
#10000
0$
#15000
b100 "
b100 .
b100 =
b10 @
1$
#20000
0$
#25000
b1000 "
b1000 .
b1000 =
b11 @
1$
#30000
0$
#35000
b1 "
b1 .
b1 =
b0 @
1$
#40000
0$
b0 '
b0 *
b0 6
#45000
b10 "
b10 .
b10 =
b1 @
1$
#50000
0$
#55000
b100 "
b100 .
b100 =
b10 @
1$
#60000
0$
#65000
b1000 "
b1000 .
b1000 =
b11 @
1$
#70000
0$
#75000
b1 "
b1 .
b1 =
b0 @
1$
